moonsense/__init__.py
moonsense/client.py
moonsense/download.py
moonsense/util.py
moonsense/cli/__init__.py
moonsense/cli/download.py
moonsense/models/__init__.py
moonsense/models/bundle_v2_pb2.py
moonsense/models/common_v2_pb2.py
moonsense/models/control_plane_v2_pb2.py
moonsense/models/data_plane_v2_pb2.py
moonsense/models/data_plane_v2_sdk_pb2.py
moonsense/models/error_reporting_pb2.py
moonsense/models/feature_pb2.py
moonsense/models/journey_feedback_pb2.py
moonsense/models/pagination_pb2.py
moonsense/models/signal_pb2.py
moonsense/models/validate_pb2.py
moonsense-0.13.1.dist-info/LICENSE
moonsense-0.13.1.dist-info/METADATA
moonsense-0.13.1.dist-info/WHEEL
moonsense-0.13.1.dist-info/entry_points.txt
moonsense-0.13.1.dist-info/top_level.txt
moonsense-0.13.1.dist-info/RECORD
