Metadata-Version: 2.1
Name: moonsense
Version: 0.13.1
Summary: Moonsense Cloud API Client
Home-page: https://github.com/moonsense/python-sdk.git
Author: Moonsense Team
Author-email: support@moonsense.io
Classifier: Programming Language :: Python :: 3
Classifier: Operating System :: OS Independent
Classifier: License :: OSI Approved :: Apache Software License
Classifier: Intended Audience :: Developers
Classifier: Intended Audience :: Science/Research
Classifier: Development Status :: 3 - Alpha
License-File: LICENSE
Requires-Dist: protobuf (<4,>=3)
Requires-Dist: requests (<3,>=2.26)
Requires-Dist: click (<9,>=8.1)
Requires-Dist: retry (<1,>=0.9)
